README.md
setup.py
iOSMonitor.egg-info/PKG-INFO
iOSMonitor.egg-info/SOURCES.txt
iOSMonitor.egg-info/dependency_links.txt
iOSMonitor.egg-info/entry_points.txt
iOSMonitor.egg-info/requires.txt
iOSMonitor.egg-info/top_level.txt
monitor/__init__.py
monitor/monitor_sysmon.py