Metadata-Version: 2.1
Name: iOSMonitor
Version: 1.0.4
Summary: iOS Monitor
Author: cfr
Author-email: 1354592998@qq.com
License: MIT
Platform: all
Requires-Python: >=3.10.0
